li_submit/__init__.py
li_submit/exceptions.py
li_submit/li_submit.py
li_submit-0.0.2.dist-info/METADATA
li_submit-0.0.2.dist-info/WHEEL
li_submit-0.0.2.dist-info/top_level.txt
li_submit-0.0.2.dist-info/RECORD
